whismur/__init__.py
whismur/__main__.py
whismur/app.py
whismur/constants.py
whismur-0.0.3.dist-info/METADATA
whismur-0.0.3.dist-info/WHEEL
whismur-0.0.3.dist-info/entry_points.txt
whismur-0.0.3.dist-info/top_level.txt
whismur-0.0.3.dist-info/RECORD
