Metadata-Version: 2.1
Name: whismur
Version: 0.0.3
Summary: Whismur
Author: datnh21
Author-email: v.datnh21@vinai.io
Classifier: Programming Language :: Python :: 3
Classifier: License :: OSI Approved :: MIT License
Classifier: Operating System :: OS Independent
Requires-Python: >=3.6
Requires-Dist: aiohttp
Requires-Dist: black
Requires-Dist: mousse
Requires-Dist: psutil
Requires-Dist: typer
